LICENSE-MIT
MANIFEST.in
README.md
setup.py
gmls/__init__.py
gmls/flask_frozen.py
gmls/static/code.css
gmls/static/markdown.css
gmls/static/style.css
gmls/templates/layout.html