Metadata-Version: 1.1
Name: gmls
Version: 0.1.1
Summary: GitHub Markdown Local Server.
Home-page: http://github.com/hit9/gmls
Author: UNKNOWN
Author-email: hit9@icloud.com
License: MIT
Keywords: github markdown local server
Platform: UNKNOWN
Classifier: Development Status :: 3 - Alpha
Classifier: Environment :: Console
Classifier: Intended Audience :: Customer Service
Classifier: License :: OSI Approved :: MIT License
Classifier: Operating System :: POSIX
Classifier: Programming Language :: Python
